ephyspy/__init__.py
ephyspy/__version__.py
ephyspy/analysis.py
ephyspy/sweeps.py
ephyspy/utils.py
ephyspy/allen_sdk/__init__.py
ephyspy/allen_sdk/ephys_extractor.py
ephyspy/allen_sdk/ephys_features.py
ephyspy/features/__init__.py
ephyspy/features/base.py
ephyspy/features/spike_features.py
ephyspy/features/sweep_features.py
ephyspy/features/sweepset_features.py
ephyspy/features/utils.py
ephyspy-0.0.8.dist-info/METADATA
ephyspy-0.0.8.dist-info/WHEEL
ephyspy-0.0.8.dist-info/licenses/LICENSE
ephyspy-0.0.8.dist-info/RECORD
