Metadata-Version: 2.4
Name: ephyspy
Version: 0.0.8
Summary: Package to extract summary statistics from electrophysiological data.
Author: Jonas Beck
License: GPL-3.0-or-later
License-File: LICENSE
Classifier: License :: OSI Approved :: GNU General Public License v3 (GPLv3)
Classifier: Programming Language :: Python :: 3
Classifier: Programming Language :: Python :: 3.12
Requires-Python: >=3.12
Requires-Dist: matplotlib>=3.4.2
Requires-Dist: numpy>=1.20.0
Requires-Dist: pandas>=1.5.3
Requires-Dist: scikit-learn>=1.1.1
Requires-Dist: scipy>=1.9.1
Provides-Extra: dev
Requires-Dist: black; extra == 'dev'
Requires-Dist: ipython>=8.12.3; extra == 'dev'
Requires-Dist: isort; extra == 'dev'
Requires-Dist: jupyter-black>=0.4.0; extra == 'dev'
Requires-Dist: jupyter>=1.1.1; extra == 'dev'
Requires-Dist: pytest-cov>=6.0.0; extra == 'dev'
Requires-Dist: pytest>=8.3.5; extra == 'dev'
Requires-Dist: seaborn>=0.13.2; extra == 'dev'
